trim_template/__init__.py
trim_template/node.py
trim_template/node_parser.py
trim_template/trim.py
trim_template-1.0.1.dist-info/LICENSE
trim_template-1.0.1.dist-info/METADATA
trim_template-1.0.1.dist-info/WHEEL
trim_template-1.0.1.dist-info/RECORD
