Metadata-Version: 2.3
Name: trim-template
Version: 1.0.1
Summary: A templating engine inspired by Ruby's Slim template engine
License: MIT
Keywords: template,trim,engine,html
Author: David Kelly
Author-email: info@futuresbright.com
Requires-Python: >=3.12
Classifier: Programming Language :: Python :: 3
Classifier: License :: OSI Approved :: MIT License
Classifier: Operating System :: OS Independent
Requires-Dist: bs4 (>=0.0.2,<0.0.3)
Requires-Dist: pytest (>=8.0.2,<9.0.0)
Requires-Dist: ruff (>=0.2.2,<0.3.0)
Project-URL: Homepage, https://github.com/opensourceame/trim-template
Project-URL: Issues, https://github.com/opensourceame/trim-template/issues
